HTPolyNet/__init__.py
HTPolyNet/ambertools.py
HTPolyNet/analyze.py
HTPolyNet/banner.py
HTPolyNet/bondlist.py
HTPolyNet/bondtemplate.py
HTPolyNet/chain.py
HTPolyNet/checkpoint.py
HTPolyNet/command.py
HTPolyNet/configuration.py
HTPolyNet/coordinates.py
HTPolyNet/countTime.py
HTPolyNet/curecontroller.py
HTPolyNet/dataframetools.py
HTPolyNet/driver.py
HTPolyNet/expandreactions.py
HTPolyNet/gromacs.py
HTPolyNet/inputcheck.py
HTPolyNet/linkcell.py
HTPolyNet/matrix4.py
HTPolyNet/molecule.py
HTPolyNet/plot.py
HTPolyNet/postsim.py
HTPolyNet/projectfilesystem.py
HTPolyNet/reaction.py
HTPolyNet/ring.py
HTPolyNet/runtime.py
HTPolyNet/software.py
HTPolyNet/stringthings.py
HTPolyNet/topocoord.py
HTPolyNet/topology.py
HTPolyNet/unused_symmetry_stuff.py
HTPolyNet/utils.py
HTPolyNet/resources/README.md
HTPolyNet/resources/__init__.py
HTPolyNet/resources/cfg/DGE-PAC-hi.yaml
HTPolyNet/resources/cfg/DGE-PAC-lo.yaml
HTPolyNet/resources/cfg/FDE-DFDA-hi.yaml
HTPolyNet/resources/cfg/FDE-DFDA-lo.yaml
HTPolyNet/resources/cfg/GMASTY-hi.yaml
HTPolyNet/resources/cfg/GMASTY-lo.yaml
HTPolyNet/resources/cfg/README.md
HTPolyNet/resources/cfg/STY.yaml
HTPolyNet/resources/cfg/pMSTY-hi.yaml
HTPolyNet/resources/cfg/pMSTY-lo.yaml
HTPolyNet/resources/cfg/pSTY-hi.yaml
HTPolyNet/resources/cfg/pSTY-lo.yaml
HTPolyNet/resources/example_depot/0-liquid-styrene.tgz
HTPolyNet/resources/example_depot/1-polystyrene.tgz
HTPolyNet/resources/example_depot/2-polymethylstyrene.tgz
HTPolyNet/resources/example_depot/3-bisgma-styrene-thermoset.tgz
HTPolyNet/resources/example_depot/4-pacm-dgeba-epoxy-thermoset.tgz
HTPolyNet/resources/example_depot/5-dfda-fde-epoxy-thermoset.tgz
HTPolyNet/resources/mdp/README.md
HTPolyNet/resources/mdp/drag-min.mdp
HTPolyNet/resources/mdp/drag-npt.mdp
HTPolyNet/resources/mdp/drag-nvt.mdp
HTPolyNet/resources/mdp/min.mdp
HTPolyNet/resources/mdp/npt.mdp
HTPolyNet/resources/mdp/nvt.mdp
HTPolyNet/resources/mdp/relax-min.mdp
HTPolyNet/resources/mdp/relax-npt.mdp
htpolynet-1.0.9.dist-info/METADATA
htpolynet-1.0.9.dist-info/WHEEL
htpolynet-1.0.9.dist-info/entry_points.txt
htpolynet-1.0.9.dist-info/licenses/LICENSE
htpolynet-1.0.9.dist-info/RECORD
