Metadata-Version: 2.1
Name: HTPolyNet
Version: 1.0.9
Summary: Automated MD System Builder for Amorphous Network Polymers
Project-URL: Source, https://github.com/AbramsGroup/HTPolyNet
Project-URL: Documentation, https://abramsgroup.github.io/HTPolyNet/
Project-URL: Bug Tracker, https://github.com/AbramsGroup/HTPolyNet/issues
Author-email: Cameron F Abrams <cfa22@drexel.edu>
License-File: LICENSE
Classifier: Development Status :: 3 - Alpha
Classifier: Intended Audience :: Science/Research
Classifier: License :: OSI Approved :: MIT License
Classifier: Operating System :: POSIX :: Linux
Classifier: Programming Language :: Python :: 3
Classifier: Topic :: Scientific/Engineering :: Chemistry
Requires-Python: >=3.9
Requires-Dist: gputil>=1.4
Requires-Dist: networkx>=3.2
Requires-Dist: numpy>=1.24
Requires-Dist: pandas>=2
Requires-Dist: parmed>=4
Requires-Dist: pyyaml>=6
Requires-Dist: requests>=2.28
Requires-Dist: scipy>=1.10
